docs/source/conf.py
matchmaker/__init__.py
matchmaker/base.py
matchmaker/matchmaker.py
matchmaker/dp/__init__.py
matchmaker/dp/dtw_loop.cpython-39-x86_64-linux-gnu.so
matchmaker/dp/dtw_loop.pyx
matchmaker/dp/oltw_arzt.py
matchmaker/dp/oltw_dixon.py
matchmaker/features/__init__.py
matchmaker/features/audio.py
matchmaker/features/midi.py
matchmaker/io/__init__.py
matchmaker/io/audio.py
matchmaker/io/mediator.py
matchmaker/io/midi.py
matchmaker/prob/__init__.py
matchmaker/prob/hmm.py
matchmaker/utils/__init__.py
matchmaker/utils/audio.py
matchmaker/utils/distances.cpython-39-x86_64-linux-gnu.so
matchmaker/utils/distances.pyx
matchmaker/utils/eval.py
matchmaker/utils/math.py
matchmaker/utils/misc.py
matchmaker/utils/processor.py
matchmaker/utils/stream.py
matchmaker/utils/symbolic.py
matchmaker/utils/tempo_models.py
matchmaker/utils/typing.py
pymatchmaker-0.2.1.dist-info/METADATA
pymatchmaker-0.2.1.dist-info/WHEEL
pymatchmaker-0.2.1.dist-info/top_level.txt
pymatchmaker-0.2.1.dist-info/RECORD
pymatchmaker-0.2.1.dist-info/licenses/LICENSE
