Metadata-Version: 2.4
Name: pymatchmaker
Version: 0.2.1
Summary: A package for real-time music alignment
Author-email: Matchmaker Development Team <carloscancinochacon@gmail.com>
License: Apache 2.0
Project-URL: Homepage, https://github.com/pymatchmaker/matchmaker
Keywords: music,alignment,midi,audio
Classifier: License :: OSI Approved :: Apache Software License
Classifier: Programming Language :: Python
Classifier: Programming Language :: Python :: 3
Classifier: Programming Language :: Cython
Classifier: Programming Language :: Python :: Implementation :: CPython
Classifier: Programming Language :: Python :: Implementation :: PyPy
Classifier: Topic :: Multimedia :: Sound/Audio
Classifier: Topic :: Multimedia :: Sound/Audio :: MIDI
Classifier: Topic :: Scientific/Engineering :: Artificial Intelligence
Requires-Python: >=3.9
License-File: LICENSE
Requires-Dist: setuptools<81,>=80.0
Requires-Dist: cython>=3.0.8
Requires-Dist: python-rtmidi>=1.5.8
Requires-Dist: mido>=1.3.2
Requires-Dist: numpy<2.0,>=1.26.3
Requires-Dist: scipy<1.15,>=1.11.4
Requires-Dist: librosa>=0.10.1
Requires-Dist: partitura>=1.7.0
Requires-Dist: progressbar2>=4.2.0
Requires-Dist: python-hiddenmarkov>=0.1.3
Requires-Dist: pyaudio>=0.2.14
Requires-Dist: pyfluidsynth>=1.3.3
Requires-Dist: matplotlib>=3.9.4
Provides-Extra: dev
Requires-Dist: black>=23.12.1; extra == "dev"
Requires-Dist: isort>=5.13.2; extra == "dev"
Requires-Dist: pre-commit>=3.6.0; extra == "dev"
Requires-Dist: ipython>=8.12.0; extra == "dev"
Requires-Dist: pyclean>=3.0.0; extra == "dev"
Requires-Dist: ruff>=0.8.2; extra == "dev"
Dynamic: license-file
